[{"estimate":2125.0,"indicator":"population_2010"},{"estimate":2516.0,"indicator":"population"},{"estimate":0.1783567134,"indicator":"poverty_rate"},{"estimate":0.1879968203,"indicator":"percent_asian"},{"estimate":0.113672496,"indicator":"percent_black"},{"estimate":0.0381558029,"indicator":"percent_hispanic"},{"estimate":0.63354531,"indicator":"percent_white"},{"estimate":0.0266295707,"indicator":"percent_other"},{"estimate":0.0178855326,"indicator":"male_under_18"},{"estimate":0.1947535771,"indicator":"male_18_to_34"},{"estimate":0.0719395866,"indicator":"male_35_to_49"},{"estimate":0.0961844197,"indicator":"male_50_to_64"},{"estimate":0.0854531002,"indicator":"male_65_and_over"},{"estimate":0.0218600954,"indicator":"female_under_18"},{"estimate":0.2802066773,"indicator":"female_18_to_34"},{"estimate":0.073926868,"indicator":"female_35_to_49"},{"estimate":0.0775039746,"indicator":"female_50_to_64"},{"estimate":0.0802861685,"indicator":"female_65_and_over"},{"estimate":62986.0,"indicator":"median_household_income"}]