[{"estimate":2288.0,"indicator":"population_2010"},{"estimate":2504.0,"indicator":"population"},{"estimate":0.098426785,"indicator":"poverty_rate"},{"estimate":0.0423322684,"indicator":"percent_asian"},{"estimate":0.0599041534,"indicator":"percent_black"},{"estimate":0.0,"indicator":"percent_hispanic"},{"estimate":0.8853833866,"indicator":"percent_white"},{"estimate":0.0123801917,"indicator":"percent_other"},{"estimate":0.0291533546,"indicator":"male_under_18"},{"estimate":0.1094249201,"indicator":"male_18_to_34"},{"estimate":0.0443290735,"indicator":"male_35_to_49"},{"estimate":0.106629393,"indicator":"male_50_to_64"},{"estimate":0.1273961661,"indicator":"male_65_and_over"},{"estimate":0.0435303514,"indicator":"female_under_18"},{"estimate":0.16014377,"indicator":"female_18_to_34"},{"estimate":0.0611022364,"indicator":"female_35_to_49"},{"estimate":0.088658147,"indicator":"female_50_to_64"},{"estimate":0.2296325879,"indicator":"female_65_and_over"},{"estimate":87917.0,"indicator":"median_household_income"}]