[{"estimate":5494.0,"indicator":"population_2010"},{"estimate":5939.0,"indicator":"population"},{"estimate":0.3503219871,"indicator":"poverty_rate"},{"estimate":0.0,"indicator":"percent_asian"},{"estimate":0.9311331874,"indicator":"percent_black"},{"estimate":0.0651624853,"indicator":"percent_hispanic"},{"estimate":0.0023572992,"indicator":"percent_white"},{"estimate":0.0013470281,"indicator":"percent_other"},{"estimate":0.231857215,"indicator":"male_under_18"},{"estimate":0.1459841724,"indicator":"male_18_to_34"},{"estimate":0.0525340966,"indicator":"male_35_to_49"},{"estimate":0.090250884,"indicator":"male_50_to_64"},{"estimate":0.0303081327,"indicator":"male_65_and_over"},{"estimate":0.1210641522,"indicator":"female_under_18"},{"estimate":0.0692035696,"indicator":"female_18_to_34"},{"estimate":0.0883987203,"indicator":"female_35_to_49"},{"estimate":0.1055733288,"indicator":"female_50_to_64"},{"estimate":0.0648257282,"indicator":"female_65_and_over"},{"estimate":33570.0,"indicator":"median_household_income"}]