[{"estimate":135892.0,"indicator":"population_2010"},{"estimate":139842.0,"indicator":"population"},{"estimate":0.1783066719,"indicator":"poverty_rate"},{"estimate":0.0262439038,"indicator":"percent_asian"},{"estimate":0.4510018449,"indicator":"percent_black"},{"estimate":0.0376996896,"indicator":"percent_hispanic"},{"estimate":0.4477767766,"indicator":"percent_white"},{"estimate":0.0372777849,"indicator":"percent_other"},{"estimate":0.0888288211,"indicator":"male_under_18"},{"estimate":0.1403154989,"indicator":"male_18_to_34"},{"estimate":0.0881208793,"indicator":"male_35_to_49"},{"estimate":0.0791822199,"indicator":"male_50_to_64"},{"estimate":0.065273666,"indicator":"male_65_and_over"},{"estimate":0.0907953262,"indicator":"female_under_18"},{"estimate":0.1541525436,"indicator":"female_18_to_34"},{"estimate":0.0930121137,"indicator":"female_35_to_49"},{"estimate":0.1059266887,"indicator":"female_50_to_64"},{"estimate":0.0943922427,"indicator":"female_65_and_over"},{"estimate":57545.0,"indicator":"median_household_income"}]