[{"estimate":26622.0,"indicator":"population_2010"},{"estimate":30486.0,"indicator":"population"},{"estimate":0.2570993579,"indicator":"poverty_rate"},{"estimate":0.0683264449,"indicator":"percent_asian"},{"estimate":0.1509545365,"indicator":"percent_black"},{"estimate":0.3593124713,"indicator":"percent_hispanic"},{"estimate":0.3905727219,"indicator":"percent_white"},{"estimate":0.0308338254,"indicator":"percent_other"},{"estimate":0.076756544,"indicator":"male_under_18"},{"estimate":0.2160335892,"indicator":"male_18_to_34"},{"estimate":0.1171685364,"indicator":"male_35_to_49"},{"estimate":0.0809551925,"indicator":"male_50_to_64"},{"estimate":0.0355245031,"indicator":"male_65_and_over"},{"estimate":0.0878764023,"indicator":"female_under_18"},{"estimate":0.1701108706,"indicator":"female_18_to_34"},{"estimate":0.0961752936,"indicator":"female_35_to_49"},{"estimate":0.0782654333,"indicator":"female_50_to_64"},{"estimate":0.0411336351,"indicator":"female_65_and_over"},{"estimate":61820.7920673077,"indicator":"median_household_income"},{"estimate":61820.7920673077,"indicator":"median_household_income"},{"estimate":61820.7920673077,"indicator":"median_household_income"},{"estimate":61820.7920673077,"indicator":"median_household_income"},{"estimate":61820.7920673077,"indicator":"median_household_income"},{"estimate":61820.7920673077,"indicator":"median_household_income"},{"estimate":61820.7920673077,"indicator":"median_household_income"},{"estimate":61820.7920673077,"indicator":"median_household_income"},{"estimate":61820.7920673077,"indicator":"median_household_income"}]