[{"estimate":3950.0,"indicator":"population_2010"},{"estimate":4199.0,"indicator":"population"},{"estimate":0.1502156205,"indicator":"poverty_rate"},{"estimate":0.0721600381,"indicator":"percent_asian"},{"estimate":0.2319599905,"indicator":"percent_black"},{"estimate":0.0209573708,"indicator":"percent_hispanic"},{"estimate":0.6465825196,"indicator":"percent_white"},{"estimate":0.028340081,"indicator":"percent_other"},{"estimate":0.0576327697,"indicator":"male_under_18"},{"estimate":0.165277447,"indicator":"male_18_to_34"},{"estimate":0.1069302215,"indicator":"male_35_to_49"},{"estimate":0.1000238152,"indicator":"male_50_to_64"},{"estimate":0.0657299357,"indicator":"male_65_and_over"},{"estimate":0.0559657061,"indicator":"female_under_18"},{"estimate":0.2045725173,"indicator":"female_18_to_34"},{"estimate":0.0833531793,"indicator":"female_35_to_49"},{"estimate":0.0676351512,"indicator":"female_50_to_64"},{"estimate":0.092879257,"indicator":"female_65_and_over"},{"estimate":83317.0,"indicator":"median_household_income"}]