[{"estimate":4942.0,"indicator":"population_2010"},{"estimate":6911.0,"indicator":"population"},{"estimate":0.0439767779,"indicator":"poverty_rate"},{"estimate":0.05484011,"indicator":"percent_asian"},{"estimate":0.2250036174,"indicator":"percent_black"},{"estimate":0.0623643467,"indicator":"percent_hispanic"},{"estimate":0.6156851396,"indicator":"percent_white"},{"estimate":0.0421067863,"indicator":"percent_other"},{"estimate":0.0586022283,"indicator":"male_under_18"},{"estimate":0.2354217913,"indicator":"male_18_to_34"},{"estimate":0.0680075242,"indicator":"male_35_to_49"},{"estimate":0.0720590363,"indicator":"male_50_to_64"},{"estimate":0.0518014759,"indicator":"male_65_and_over"},{"estimate":0.077557517,"indicator":"female_under_18"},{"estimate":0.2079293879,"indicator":"female_18_to_34"},{"estimate":0.0856605412,"indicator":"female_35_to_49"},{"estimate":0.0680075242,"indicator":"female_50_to_64"},{"estimate":0.0749529735,"indicator":"female_65_and_over"},{"estimate":118351.0,"indicator":"median_household_income"}]